LICENSE
README.md
setup.py
HoylJsonManager/__init__.py
HoylJsonManager/checker.py
HoylJsonManager/dropKey.py
HoylJsonManager/get.py
HoylJsonManager/update.py
hoyl_json_manager.egg-info/PKG-INFO
hoyl_json_manager.egg-info/SOURCES.txt
hoyl_json_manager.egg-info/dependency_links.txt
hoyl_json_manager.egg-info/top_level.txt