Metadata-Version: 2.1
Name: hoyl-json-manager
Version: 1.1
Summary: Pequena biblioteca para validação e manipulação de JSONs
Author: Alan Reis Anjos
Author-email: alanreisanjo@gmail.com
License: MIT License
Keywords: Hoyl JSON Manager
License-File: LICENSE
